{"title":"뉴스타파 ─ 뉴스 ─ 교육","url":"http://newstapa.org/category/%EA%B5%90%EC%9C%A1","favicon":"http://newstapa.org/category/favicon.ico","elements":[{"title":"검찰이 면죄부 준 조선일보 사돈의 리조트 장사","contents":"검찰이 면죄부 준 조선일보 사돈의 리조트 장사","link":"http://newstapa.org/article/12rhs","retrieved":1658361600000,"image":"https://d1lawh9lju1xqd.cloudfront.net/2022/07/21134648-5D1D-4D13-48CB-QAG00PEPH3805E5X9ASQ.png"},{"title":"한국인 운영 ‘해적학술지’ 확인…한동훈 처형과의 관계는?","contents":"한국인 운영 ‘해적학술지’ 확인…한동훈 처형과의 관계는?","link":"http://newstapa.org/article/V60lw","retrieved":1657670400000,"image":"https://d1lawh9lju1xqd.cloudfront.net/2022/07/13142309-F854-FE74-CEA7-SR9JNWV9C1QUWBN7QKO7.jpg"},{"title":"미국 논문 쓰면서 '브라질 주민 데이터' 도용...한동훈 처조카 논문 데이터 위조","contents":"미국 논문 쓰면서 '브라질 주민 데이터' 도용...한동훈 처조카 논문 데이터 위조","link":"http://newstapa.org/article/MBd_O","retrieved":1657152000000,"image":"https://d1lawh9lju1xqd.cloudfront.net/2022/07/07195752-F2FE-F1FB-A3F2-9B8Q2HYEEIPZFRYWZURD.jpg"},{"title":"통계 뒤죽박죽 베낀 엉터리 논문 수두룩... 한동훈 처조카 데이터 조작","contents":"통계 뒤죽박죽 베낀 엉터리 논문 수두룩... 한동훈 처조카 데이터 조작","link":"http://newstapa.org/article/3rZeH","retrieved":1657152000000,"image":"https://d1lawh9lju1xqd.cloudfront.net/2022/07/08110847-E4F4-911D-B973-YVXPX5KJAQ7QW257J0W2.jpg"},{"title":"한동훈 처조카 논문 데이터 위조... 촛불집회에 다인종 참여?","contents":"한동훈 처조카 논문 데이터 위조... 촛불집회에 다인종 참여?","link":"http://newstapa.org/article/DWQ-x","retrieved":1656979200000,"image":"https://d1lawh9lju1xqd.cloudfront.net/2022/07/05155739-8343-A388-3868-CAA94DPSQQ0EJJ999EMI.jpg"},{"title":"[주간 뉴스타파] 한동훈 처가와 '산호세 허위스펙 네트워크'","contents":"[주간 뉴스타파] 한동훈 처가와 '산호세 허위스펙 네트워크'","link":"http://newstapa.org/article/kANwK","retrieved":1656547200000,"image":"https://d1lawh9lju1xqd.cloudfront.net/2022/06/30174705-6CC9-4ECD-12E8-RNOMF4954U6JKL0XYERV.jpg"},{"title":"한동훈 처가 4명 연루 '허위 스펙 네트워크' 분석","contents":"한동훈 처가 4명 연루 '허위 스펙 네트워크' 분석","link":"http://newstapa.org/article/n5XnJ","retrieved":1656547200000,"image":"https://d1lawh9lju1xqd.cloudfront.net/2022/06/30160453-2EC7-1308-6581-JSGV50KFN02N1EAWIYPE.jpg"},{"title":"IEEE, 한동훈 장관 장녀의 '국제 학술대회 표절 논문' 조사 착수","contents":"IEEE, 한동훈 장관 장녀의 '국제 학술대회 표절 논문' 조사 착수","link":"http://newstapa.org/article/NS4I6","retrieved":1656460800000,"image":"https://d1lawh9lju1xqd.cloudfront.net/2022/06/29121146-AA59-19A2-CF61-2H6YUB6MXT9MKIE7KKH9.jpg"},{"title":"윤석열 정부, 중징계 대상 '국정교과서 책임자' 요직에 또 영전","contents":"윤석열 정부, 중징계 대상 '국정교과서 책임자' 요직에 또 영전","link":"http://newstapa.org/article/izcdK","retrieved":1653350400000,"image":"https://d1lawh9lju1xqd.cloudfront.net/2022/05/23210243-9FD0-D61E-25DF-2KFXH7J0OOBTFT584NWE.jpg"},{"title":"권성연 교육비서관, 찬성 여론 조작 등 '박근혜 역사교과서 국정화' 실무 주도","contents":"권성연 교육비서관, 찬성 여론 조작 등 '박근혜 역사교과서 국정화' 실무 주도","link":"http://newstapa.org/article/rQ3_G","retrieved":1652659200000,"image":"https://d1lawh9lju1xqd.cloudfront.net/2022/05/15075459-7D86-AA71-001C-CFIV8SSGA1WKUDVNEHQ4.jpg"},{"title":"[변화]'직원 폭행' 협성대 박명래 총장, 사건 10개월 만에 해임","contents":"[변화]'직원 폭행' 협성대 박명래 총장, 사건 10개월 만에 해임","link":"http://newstapa.org/article/op4gx","retrieved":1651795200000,"image":"https://d1lawh9lju1xqd.cloudfront.net/2022/05/06154441-6F1A-6899-5691-GTEA2ZQ1P0HNCYUP7HQQ.jpg"},{"title":"김인철, 외대 총장 때 석좌교수 'MB·박근혜 정권 출신' 다수","contents":"김인철, 외대 총장 때 석좌교수 'MB·박근혜 정권 출신' 다수","link":"http://newstapa.org/article/4qodk","retrieved":1651017600000,"image":"https://d1lawh9lju1xqd.cloudfront.net/2022/04/27104614-A3F2-A9C3-55D1-N8JRG2Z0BZ8U415N5KBS.jpg"},{"title":"같은 날, 같은 장소, 같은 금액...김인철 후보자의 외대와 대교협 '수상한 업무추진비'","contents":"같은 날, 같은 장소, 같은 금액...김인철 후보자의 외대와 대교협 '수상한 업무추진비'","link":"http://newstapa.org/article/x3WWB","retrieved":1650931200000,"image":"https://d1lawh9lju1xqd.cloudfront.net/2022/04/26205045-A28B-7763-023C-UF9WDH51OMDXDUJINT5B.jpg"},{"title":"[현장에서] 폭력 총장이 복귀했습니다","contents":"[현장에서] 폭력 총장이 복귀했습니다","link":"http://newstapa.org/article/jT3Ww","retrieved":1648684800000,"image":"https://d1lawh9lju1xqd.cloudfront.net/2022/03/31102813-1C49-B658-D768-5OGNHQA47I3AE2L1F1D0.jpg"},{"title":"[변화] 법원 \"권익위의 카이스트 제보자 신분보장 요구 각하는 위법\"","contents":"[변화] 법원 \"권익위의 카이스트 제보자 신분보장 요구 각하는 위법\"","link":"http://newstapa.org/article/a8uRJ","retrieved":1637020800000,"image":"https://d1lawh9lju1xqd.cloudfront.net/2021/11/16150118-3D62-45CD-0AEF-RKQO6WIA3SJFVFT0T9AA.jpg"},{"title":"[변화]'직원 폭행' 협성대 총장, 넉 달 만에 직위 해제","contents":"[변화]'직원 폭행' 협성대 총장, 넉 달 만에 직위 해제","link":"http://newstapa.org/article/LG398","retrieved":1635120000000,"image":"https://d1lawh9lju1xqd.cloudfront.net/2021/10/25170707-3C7B-EA82-5A85-ML8FPS8J1QH0Z73F129U.jpg"}]}