{"title":"뉴스타파 ─ 뉴스","url":"http://newstapa.org/recent","favicon":"http://newstapa.org/favicon.ico","elements":[{"title":"비트코인 첫 신고 공직자 나왔다... 그러나 '갈팡질팡' 안내에 재산 왜곡까지","contents":"비트코인 첫 신고 공직자 나왔다... 그러나 '갈팡질팡' 안내에 재산 왜곡까지","link":"http://newstapa.org/article/qT2kI","retrieved":1680480000000,"image":"https://d1lawh9lju1xqd.cloudfront.net/2023/04/03132542-0D76-1153-925B-LE33AW0HKNFBUHE189A2.jpg"},{"title":"\"해운대구광역시\"에 틀린 덧셈까지... 오류투성이 재산공개 시스템","contents":"\"해운대구광역시\"에 틀린 덧셈까지... 오류투성이 재산공개 시스템","link":"http://newstapa.org/article/Sba6S","retrieved":1680480000000,"image":"https://d1lawh9lju1xqd.cloudfront.net/2023/04/02210017-72B4-2621-617A-0EI9U4SFHIGQ0A4OMIXE.png"},{"title":"일본 전역에 울려 퍼진 김복동의 외침 “일본 정부는 사죄하라”","contents":"일본 전역에 울려 퍼진 김복동의 외침 “일본 정부는 사죄하라”","link":"http://newstapa.org/article/hMc1D","retrieved":1680220800000,"image":"https://d1lawh9lju1xqd.cloudfront.net/2023/03/31184759-E0E3-6E31-011F-XDK7HUNEJH1XKV4S7T9H.jpg"},{"title":"[사법개혁 프로젝트 2] 한동훈 검사, 윤석열 검사, 그리고 조선총독부 다마나 검사...헌법 위에 시행령②","contents":"[사법개혁 프로젝트 2] 한동훈 검사, 윤석열 검사, 그리고 조선총독부 다마나 검사...헌법 위에 시행령②","link":"http://newstapa.org/article/DP5pY","retrieved":1680220800000,"image":"https://d1lawh9lju1xqd.cloudfront.net/2023/03/31161612-C0E1-A363-C2C3-2D867DKADMOSJ4FIXX1G.jpg"},{"title":"[삼림파괴 주식회사④]목재펠릿 공장 분진 심각, 실내까지 침투","contents":"[삼림파괴 주식회사④]목재펠릿 공장 분진 심각, 실내까지 침투","link":"http://newstapa.org/article/nZUU3","retrieved":1680220800000,"image":"https://d1lawh9lju1xqd.cloudfront.net/2023/03/30150520-9340-5BCD-BB4B-BKXC5MBVK4HGUU27HGRT.jpg"},{"title":"[이예람 중사 사건 재판 지상 중계]⑥ '2차 가해' 정황 알고도 수사 안 한 군검사","contents":"[이예람 중사 사건 재판 지상 중계]⑥ '2차 가해' 정황 알고도 수사 안 한 군검사","link":"http://newstapa.org/article/NkJgL","retrieved":1680220800000,"image":"https://d1lawh9lju1xqd.cloudfront.net/2023/03/30214427-C6BF-12EA-47A2-NW35B6T7RCE8YQ7Q855P.jpg"},{"title":"[주간 뉴스타파] 세상이 청년에게 말하지 않는, 진짜 연금개혁 이야기","contents":"[주간 뉴스타파] 세상이 청년에게 말하지 않는, 진짜 연금개혁 이야기","link":"http://newstapa.org/article/kST11","retrieved":1680134400000,"image":"https://d1lawh9lju1xqd.cloudfront.net/2023/03/30170430-395D-F04C-3735-1SU7AX0NKMYSIRE28SML.jpg"},{"title":"[대장동 X파일] 화천대유-하나은행 묶어준 뒷배는 SK계열사, 킨앤이었다","contents":"[대장동 X파일] 화천대유-하나은행 묶어준 뒷배는 SK계열사, 킨앤이었다","link":"http://newstapa.org/article/3ylfn","retrieved":1680134400000,"image":"https://d1lawh9lju1xqd.cloudfront.net/2023/03/30082016-B873-4E9D-02D8-X4BRQ9DHAMQSZFD8V8CG.jpg"},{"title":"검찰이 덮은 '강현도 오산 부시장 뇌물 사건'... 경찰은 '기소의견 송치'","contents":"검찰이 덮은 '강현도 오산 부시장 뇌물 사건'... 경찰은 '기소의견 송치'","link":"http://newstapa.org/article/wEr3r","retrieved":1680048000000,"image":"https://d1lawh9lju1xqd.cloudfront.net/2023/03/29144006-446A-EB61-A301-AW64CFJWG35ERM3O1I5M.jpg"},{"title":"[대장동 X파일] ‘검찰 버전 녹취록’에 드러난 수사 무마… 남욱 “수사관이 복수해준대요”","contents":"[대장동 X파일] ‘검찰 버전 녹취록’에 드러난 수사 무마… 남욱 “수사관이 복수해준대요”","link":"http://newstapa.org/article/IsaTh","retrieved":1680048000000,"image":"https://d1lawh9lju1xqd.cloudfront.net/2023/03/29102338-90A8-FB58-6BCE-KDFEYY990S95P0J62TPF.jpg"},{"title":"임은정 vs 한동훈, 누가 부적격 검사인가1","contents":"임은정 vs 한동훈, 누가 부적격 검사인가1","link":"http://newstapa.org/article/QPOFr","retrieved":1679961600000,"image":"https://d1lawh9lju1xqd.cloudfront.net/2023/03/28152046-1DCE-230F-EC4F-N8GU0PT3W1CFM0M4Y9HM.jpg"},{"title":"[대장동 X파일]\"곽상도가 수사 막아줬다\"는 김만배 자백에도, 검찰은 또 수사 뭉갰다","contents":"[대장동 X파일]\"곽상도가 수사 막아줬다\"는 김만배 자백에도, 검찰은 또 수사 뭉갰다","link":"http://newstapa.org/article/kpJoz","retrieved":1679961600000,"image":"https://d1lawh9lju1xqd.cloudfront.net/2023/03/27155448-C42B-1DC5-40A2-KF4TLFXQCR69J61O8989.jpg"},{"title":"윤석열 정부, 대통령기록물법 무시...알 권리 침해 우려","contents":"윤석열 정부, 대통령기록물법 무시...알 권리 침해 우려","link":"http://newstapa.org/article/NIsWS","retrieved":1679875200000,"image":"https://d1lawh9lju1xqd.cloudfront.net/2023/03/27150825-9A96-1C58-DD5D-ESCE30Z86WHXA4C06S3P.jpg"},{"title":"국민을 속인 감사원의 거짓 보고서","contents":"국민을 속인 감사원의 거짓 보고서","link":"http://newstapa.org/article/l1XVG","retrieved":1679875200000,"image":"https://d1lawh9lju1xqd.cloudfront.net/2023/03/24145011-CAB2-0F02-108D-QI3R59NM1L855J0Q8B0N.jpg"},{"title":"[대장동 X파일] SK계열사 킨앤파트너스, 전주(錢主)가 아닌 불법의 동업자였다","contents":"[대장동 X파일] SK계열사 킨앤파트너스, 전주(錢主)가 아닌 불법의 동업자였다","link":"http://newstapa.org/article/0xECn","retrieved":1679616000000,"image":"https://d1lawh9lju1xqd.cloudfront.net/2023/03/23113523-C3D5-E317-4C1B-2NZKAP83Q4HHMXOHCRIH.jpg"},{"title":"[주간 뉴스타파] 뉴스타파 vs 대통령실, 예산 공개 소송 시작","contents":"[주간 뉴스타파] 뉴스타파 vs 대통령실, 예산 공개 소송 시작","link":"http://newstapa.org/article/xzGxJ","retrieved":1679529600000,"image":"https://d1lawh9lju1xqd.cloudfront.net/2023/03/23184541-3975-1660-1213-PDZY8SXNM1ZSZUQPSX7O.jpg"}]}